calypso/__init__.py
calypso/model/__init__.py
calypso/model/scraper.py
calypso/service/__init__.py
calypso/service/binsx.py
calypso/service/coomer.py
calypso/service/gotanynudes.py
calypso/service/leakedzone.py
calypso/service/openfoodfacts_v3.py
calypso/service/voiranime.py
calypso/service/voirdrama.py
pycalypso-0.1.7.dist-info/licenses/LICENSE.txt
pycalypso-0.1.7.dist-info/METADATA
pycalypso-0.1.7.dist-info/WHEEL
pycalypso-0.1.7.dist-info/top_level.txt
pycalypso-0.1.7.dist-info/RECORD
