Metadata-Version: 2.4
Name: pycalypso
Version: 0.1.7
Summary: Custom Python library for web scraping, flexible and tailored to your projects
Home-page: https://github.com/Game-K-Hack/calypso
Author: Game_K
Author-email: game_k@laposte.net
Classifier: Programming Language :: Python :: 3
Classifier: License :: OSI Approved :: MIT License
Classifier: Operating System :: OS Independent
Requires-Python: >=3.7
License-File: LICENSE.txt
Dynamic: author
Dynamic: author-email
Dynamic: classifier
Dynamic: description
Dynamic: description-content-type
Dynamic: home-page
Dynamic: license-file
Dynamic: requires-python
Dynamic: summary
